{"id": "3b18e6fff7c1ad7c", "content": "MODULE: cosmos.memory.unified_memory\nFILE: cosmos/memory/unified_memory.py (1106 lines)\nCATEGORY: memory\n\nDESCRIPTION: COSMOS UNIFIED MEMORY ARCHITECTURE\n=======================================\n\nThe most advanced multi-layered memory system integrating all 18 memory types\ninto a cohesive architecture with lightweight session references for agents.\n\nMemory Systems Integrated:\n1.  Working Memory       - Current task s\n\nCLASSES:\n- MemoryTier(Enum): Memory storage tiers by access speed/freshness\n- MemoryDomain(Enum): Semantic domains for routing\n- QueryIntent(Enum): Types of memory queries\n- SessionReference: Lightweight token for agent memory access.\n\nAgents receive this at session start\n  Methods: def add_query(self, query: str)\n  Methods: def update_context(self, topics: List[str]=None, entities: List[str]=None, projects: List[str]=None)\n  Methods: def get_context_hints(self) -> Dict\n  Methods: def to_dict(self) -> Dict\n- MemoryResult: Unified result from any memory system\n  Methods: def to_dict(self) -> Dict\n- RoutingDecision: Decision about which memory systems to query\n- MemoryRouter: Routes queries to optimal memory systems based on:\n- Query intent classification\n  Methods: def classify_intent(self, query: str) -> QueryIntent\n  Methods: def classify_domain(self, query: str, context: Dict) -> List[MemoryDomain]\n  Methods: def route(self, query: str, session: SessionReference, max_latency_ms: int=None) -> RoutingDecision\n- MemoryPipeline: Processing pipeline for memory operations.\n\nStages:\n1. Pre-process: Expand query\n  Methods: async def process(self, query: str, session: SessionReference, systems: Dict[str, Any], top_k: int=1\n- UnifiedMemoryAPI: Single interface for all 18 memory systems.\n\nProvides:\n- Session management with\n  Methods: async def initialize(self)\n  Methods: def create_session(self, agent_id: str) -> SessionReference\n  Methods: def get_session(self, session_id: str) -> Optional[SessionReference]\n  Methods: def end_session(self, session_id: str)\n  Methods: async def query(self, query: str, session: SessionReference, top_k: int=10, systems: List[str]=None,\n  Methods: async def remember(self, content: str, session: SessionReference, tags: List[str]=None, importance: \n  Methods: async def forget(self, memory_id: str, session: SessionReference) -> bool\n  Methods: async def get_timeline(self, session: SessionReference, start_date: datetime=None, end_date: datetim\n\nPUBLIC FUNCTIONS:\n- def get_unified_memory_api() -> UnifiedMemoryAPI\n- async def mcp_create_session(agent_id: str) -> Dict\n- async def mcp_query_memory(query: str, session_id: str, top_k: int=10, systems: List[str]=None) -> List[Dict]\n- async def mcp_remember(content: str, session_id: str, tags: List[str]=None, importance: float=0.5) -> Dict\n- async def mcp_get_related(entity_or_topic: str, session_id: str, depth: int=2) -> List[Dict]\n- async def mcp_get_memory_stats() -> Dict", "metadata": {"type": "codebase_module", "category": "memory", "filepath": "cosmos/memory/unified_memory.py", "line_count": 1106}, "created_at": "2026-03-15T09:06:26.706772", "tags": ["codebase", "module", "memory", "MemoryTier", "MemoryDomain", "QueryIntent", "SessionReference", "MemoryResult", "RoutingDecision", "MemoryRouter", "MemoryPipeline", "UnifiedMemoryAPI", "get_unified_memory_api", "mcp_create_session", "mcp_query_memory", "mcp_remember", "mcp_get_related", "mcp_get_memory_stats", "unified_memory"], "cluster_id": null, "retrieval_count": 0, "last_retrieved": null, "relevance_feedback": 0.0}