{"id": "60b89ca3d4011352", "content": "MODULE: cosmos.mcp_server.resources\nFILE: cosmos/mcp_server/resources.py (226 lines)\nCATEGORY: mcp_server\n\nDESCRIPTION: cosmos Resources - MCP Resource Implementations\n\nProvides streaming resources:\n- Memory context\n- Knowledge graph\n- Agent status\n- Evolution metrics\n\nCLASSES:\n- cosmosResources: Resource implementations for the MCP server.\n\nProvides read-only access to cosmo\n  Methods: async def get_recent_context(self, max_length: int=4000) -> str\n  Methods: async def get_memory_summary(self) -> str\n  Methods: async def get_knowledge_graph_json(self) -> str\n  Methods: async def get_active_agents_json(self) -> str\n  Methods: async def get_fitness_metrics_json(self) -> str\n  Methods: async def get_system_status_json(self) -> str\n  Methods: async def get_conversation_history(self, max_turns: int=20) -> str\n  Methods: async def get_working_memory_summary(self) -> str\n\nPUBLIC FUNCTIONS:\n- async def handle_resource_read(resources: cosmosResources, uri: str) -> str", "metadata": {"type": "codebase_module", "category": "mcp_server", "filepath": "cosmos/mcp_server/resources.py", "line_count": 226}, "created_at": "2026-03-19T18:35:04.027416", "tags": ["codebase", "module", "mcp_server", "cosmosResources", "handle_resource_read", "resources"], "cluster_id": null, "retrieval_count": 0, "last_retrieved": null, "relevance_feedback": 0.0}