{"id": "8542aa874670f866", "content": "MODULE: cosmos.integration.vision.reconstruction\nFILE: cosmos/integration/vision/reconstruction.py (106 lines)\nCATEGORY: integration\n\nDESCRIPTION: cosmos 3D Scene Reconstruction - Structure from Motion (SfM) Core.\n\n\"I can see the depth, and the depth sees me!\"\n\nThis module implements:\n1. Feature Matching across keyframes (multi-view geometry).\n2. Fundamental Matrix estimation.\n3. Sparse Point Cloud generation (simulated or via OpenCV Triangula\n\nCLASSES:\n- Point3D\n- ReconstructedScene\n- ReconstructionEngine\n  Methods: def process_frames(self, frames: List[Image.Image]) -> ReconstructedScene\n\nPUBLIC FUNCTIONS:\n- def create_reconstruction_engine()", "metadata": {"type": "codebase_module", "category": "integration", "filepath": "cosmos/integration/vision/reconstruction.py", "line_count": 106}, "created_at": "2026-03-18T23:42:09.847626", "tags": ["codebase", "module", "integration", "Point3D", "ReconstructedScene", "ReconstructionEngine", "create_reconstruction_engine", "reconstruction"], "cluster_id": null, "retrieval_count": 0, "last_retrieved": null, "relevance_feedback": 0.0}