{"id": "ba83a6ee90241203", "content": "MODULE: cosmos.cicd.__init__\nFILE: cosmos/cicd/__init__.py (27 lines)\nCATEGORY: cicd\n\nDESCRIPTION: cosmos CI/CD Pipeline Management\n\n\"Good news, everyone! The build passed!\"\n\nComprehensive CI/CD integration for GitHub Actions, GitLab CI, and Jenkins.", "metadata": {"type": "codebase_module", "category": "cicd", "filepath": "cosmos/cicd/__init__.py", "line_count": 27}, "created_at": "2026-03-16T03:04:27.082481", "tags": ["codebase", "module", "cicd", "__init__"], "cluster_id": null, "retrieval_count": 0, "last_retrieved": null, "relevance_feedback": 0.0}