{"id": "e1e2c6f20ae908af", "content": "MODULE: cosmos.integration.financial.memecoin_tracker\nFILE: cosmos/integration/financial/memecoin_tracker.py (283 lines)\nCATEGORY: integration\n\nDESCRIPTION: cosmos Memecoin Tracker - Pump.fun & Bags.fm.\n\n\"Tracking the degens, one bonding curve at a time.\"\n\nCLASSES:\n- BagsClaimMode(Enum): Mode for fetching claim events.\n- BagsTokenLaunch: Token launch configuration for Bags.fm.\n- BagsFeeShareConfig: Fee share configuration - up to 100 fee claimers.\n- BagsSwapParams: Parameters for swap transactions.\n- MemecoinSkill\n  Methods: def set_bags_api_key(self, api_key: str)\n  Methods: async def get_pump_token(self, mint_address: str) -> Dict\n  Methods: async def get_pump_new_tokens(self, limit: int=10) -> List[Dict]\n  Methods: async def get_bags_token(self, token_address: str) -> Dict\n  Methods: async def get_bags_trending(self) -> List[Dict]\n  Methods: async def get_token_launch_creators(self, token_mint: str) -> Dict\n  Methods: async def get_token_lifetime_fees(self, token_mint: str) -> Dict\n  Methods: async def get_token_claim_events(self, token_mint: str, mode: BagsClaimMode=BagsClaimMode.OFFSET, of", "metadata": {"type": "codebase_module", "category": "integration", "filepath": "cosmos/integration/financial/memecoin_tracker.py", "line_count": 283}, "created_at": "2026-03-19T18:20:30.453637", "tags": ["codebase", "module", "integration", "BagsClaimMode", "BagsTokenLaunch", "BagsFeeShareConfig", "BagsSwapParams", "MemecoinSkill", "memecoin_tracker"], "cluster_id": null, "retrieval_count": 0, "last_retrieved": null, "relevance_feedback": 0.0}